z3tracker/__init__.py
z3tracker/__main__.py
z3tracker/gui.py
z3tracker/main.py
z3tracker/version.py
z3tracker/autotracker/__init__.py
z3tracker/autotracker/addresses.py
z3tracker/autotracker/autotracker.py
z3tracker/autotracker/exceptions.py
z3tracker/autotracker/items.py
z3tracker/autotracker/usb2snes.py
z3tracker/config/__init__.py
z3tracker/config/config.py
z3tracker/config/conversion.py
z3tracker/config/default.py
z3tracker/config/globals.py
z3tracker/config/images.py
z3tracker/dungeons/__init__.py
z3tracker/dungeons/dungeonobj.py
z3tracker/dungeons/dungeons.py
z3tracker/dungeons/lists.py
z3tracker/dungeons/storage.py
z3tracker/entrances/__init__.py
z3tracker/entrances/entrances.py
z3tracker/entrances/storage.py
z3tracker/gui-tkinter/__init__.py
z3tracker/gui-tkinter/autotracker.py
z3tracker/gui-tkinter/config.py
z3tracker/gui-tkinter/dark.py
z3tracker/gui-tkinter/dungeons.py
z3tracker/gui-tkinter/environ.py
z3tracker/gui-tkinter/help.py
z3tracker/gui-tkinter/interface.py
z3tracker/gui-tkinter/items.py
z3tracker/gui-tkinter/light.py
z3tracker/gui-tkinter/maps.py
z3tracker/gui-tkinter/misc.py
z3tracker/gui-tkinter/ttkstyle.py
z3tracker/items/__init__.py
z3tracker/items/itemobj.py
z3tracker/items/items.py
z3tracker/items/lists.py
z3tracker/items/storage.py
z3tracker/maps/__init__.py
z3tracker/maps/maps.py
z3tracker/maps/storage.py
z3tracker/ruleset/__init__.py
z3tracker/ruleset/vt8/__init__.py
z3tracker/ruleset/vt8/castle.py
z3tracker/ruleset/vt8/darkpalace.py
z3tracker/ruleset/vt8/darkworld_east.py
z3tracker/ruleset/vt8/darkworld_north.py
z3tracker/ruleset/vt8/darkworld_south.py
z3tracker/ruleset/vt8/deathmountain.py
z3tracker/ruleset/vt8/desert.py
z3tracker/ruleset/vt8/dungeons.py
z3tracker/ruleset/vt8/ganonstower.py
z3tracker/ruleset/vt8/hebra.py
z3tracker/ruleset/vt8/icepalace.py
z3tracker/ruleset/vt8/kakariko.py
z3tracker/ruleset/vt8/lightworld_east.py
z3tracker/ruleset/vt8/lightworld_north.py
z3tracker/ruleset/vt8/lightworld_south.py
z3_tracker-0.9.12.dist-info/LICENCE
z3_tracker-0.9.12.dist-info/METADATA
z3_tracker-0.9.12.dist-info/WHEEL
z3_tracker-0.9.12.dist-info/entry_points.txt
z3_tracker-0.9.12.dist-info/top_level.txt
z3_tracker-0.9.12.dist-info/RECORD
