Metadata-Version: 2.1
Name: z3-tracker
Version: 0.9.12
Summary: Helper program for Link to the Past randomiser
Home-page: https://www.github.com/feneg/z3-tracker
Author: Feneg
Author-email: UNKNOWN
License: UNKNOWN
Platform: UNKNOWN
Classifier: Development Status :: 4 - Beta
Classifier: License :: OSI Approved :: MIT License
Classifier: Programming Language :: Python :: 3.6
Classifier: Topic :: Games/Entertainment
Classifier: Topic :: Utilities
